sdk/__init__.py
am_trade_sdk-1.0.0.dist-info/METADATA
am_trade_sdk-1.0.0.dist-info/WHEEL
am_trade_sdk-1.0.0.dist-info/top_level.txt
am_trade_sdk-1.0.0.dist-info/RECORD
