Metadata-Version: 2.4
Name: am-trade-sdk
Version: 1.0.0
Summary: Python SDK for AM Trade Management System
Author-email: AM Portfolio <support@am-portfolio.com>
License: MIT
Project-URL: Homepage, https://github.com/AM-Portfolio/am-trade-management
Project-URL: Repository, https://github.com/AM-Portfolio/am-trade-management.git
Project-URL: Bug Tracker, https://github.com/AM-Portfolio/am-trade-management/issues
Keywords: trading,sdk,api-client,portfolio,analytics
Classifier: Development Status :: 4 - Beta
Classifier: Intended Audience :: Developers
Classifier: License :: OSI Approved :: MIT License
Classifier: Programming Language :: Python :: 3
Classifier: Programming Language :: Python :: 3.8
Classifier: Programming Language :: Python :: 3.9
Classifier: Programming Language :: Python :: 3.10
Classifier: Programming Language :: Python :: 3.11
Classifier: Programming Language :: Python :: 3.12
Classifier: Topic :: Software Development :: Libraries :: Python Modules
Requires-Python: >=3.8
Requires-Dist: requests>=2.28.0
Requires-Dist: pydantic>=1.10.0
Requires-Dist: python-dotenv>=0.19.0
Requires-Dist: typing-extensions>=4.0.0
Requires-Dist: PyJWT>=2.8.0
Provides-Extra: dev
Requires-Dist: pytest>=7.0.0; extra == "dev"
Requires-Dist: pytest-cov>=4.0.0; extra == "dev"
Requires-Dist: pytest-asyncio>=0.21.0; extra == "dev"
Requires-Dist: black>=23.0.0; extra == "dev"
Requires-Dist: flake8>=6.0.0; extra == "dev"
Requires-Dist: mypy>=1.0.0; extra == "dev"
Requires-Dist: isort>=5.12.0; extra == "dev"
Provides-Extra: docs
Requires-Dist: sphinx>=6.0.0; extra == "docs"
Requires-Dist: sphinx-rtd-theme>=1.2.0; extra == "docs"
Requires-Dist: sphinx-autodoc-typehints>=1.20.0; extra == "docs"
